flat_profiler/__about__.py
flat_profiler/__init__.py
flat_profiler/flat_profiler.py
flat_profiler/performance.py
flat_profiler-0.2.2.dist-info/METADATA
flat_profiler-0.2.2.dist-info/WHEEL
flat_profiler-0.2.2.dist-info/licenses/LICENSE
flat_profiler-0.2.2.dist-info/RECORD
