Metadata-Version: 2.1
Name: flat_profiler
Version: 0.2.2
Summary: Python flat profiling tool.
Project-URL: Homepage, https://github.com/DanWehr/flat_profiler
Project-URL: Documentation, https://github.com/DanWehr/flat_profiler#readme
Project-URL: Issues, https://github.com/DanWehr/flat_profiler/issues
Project-URL: Repository, https://github.com/DanWehr/flat_profiler.git
Author-email: Daniel Wehr <danwehr@gmail.com>
License-Expression: MIT
License-File: LICENSE
Classifier: Development Status :: 3 - Alpha
Classifier: Intended Audience :: Developers
Classifier: License :: OSI Approved :: MIT License
Classifier: Operating System :: OS Independent
Classifier: Programming Language :: Python :: 3
Classifier: Programming Language :: Python :: 3.10
Classifier: Programming Language :: Python :: 3.11
Classifier: Programming Language :: Python :: 3.12
Classifier: Topic :: Software Development :: Libraries :: Python Modules
Classifier: Topic :: Utilities
Requires-Python: >=3.10
Requires-Dist: recompyle<0.5.0,>=0.4.1
